Classfile /Users/mk/Desktop/temp/java-opcode/build/src/Main.class
  Last modified 2024. 3. 26.; size 1348 bytes
  SHA-256 checksum d2c6c3d3ec0faf84407f065fc9db9810dbdf173124786e1e3d4603e79a0a7290
  Compiled from "Main.java"
public class src.Main
  minor version: 0
  major version: 61
  flags: (0x0021) ACC_PUBLIC, ACC_SUPER
  this_class: #52                         // src/Main
  super_class: #2                         // java/lang/Object
  interfaces: 0, fields: 0, methods: 2, attributes: 3
Constant pool:
   #1 = Methodref          #2.#3          // java/lang/Object."<init>":()V
   #2 = Class              #4             // java/lang/Object
   #3 = NameAndType        #5:#6          // "<init>":()V
   #4 = Utf8               java/lang/Object
   #5 = Utf8               <init>
   #6 = Utf8               ()V
   #7 = Fieldref           #8.#9          // java/lang/System.out:Ljava/io/PrintStream;
   #8 = Class              #10            // java/lang/System
   #9 = NameAndType        #11:#12        // out:Ljava/io/PrintStream;
  #10 = Utf8               java/lang/System
  #11 = Utf8               out
  #12 = Utf8               Ljava/io/PrintStream;
  #13 = String             #14            // Before new Person
  #14 = Utf8               Before new Person
  #15 = Methodref          #16.#17        // java/io/PrintStream.println:(Ljava/lang/String;)V
  #16 = Class              #18            // java/io/PrintStream
  #17 = NameAndType        #19:#20        // println:(Ljava/lang/String;)V
  #18 = Utf8               java/io/PrintStream
  #19 = Utf8               println
  #20 = Utf8               (Ljava/lang/String;)V
  #21 = Class              #22            // src/Person
  #22 = Utf8               src/Person
  #23 = String             #24            // alice
  #24 = Utf8               alice
  #25 = Methodref          #21.#26        // src/Person."<init>":(ILjava/lang/String;)V
  #26 = NameAndType        #5:#27         // "<init>":(ILjava/lang/String;)V
  #27 = Utf8               (ILjava/lang/String;)V
  #28 = String             #29            // new Person : alice
  #29 = Utf8               new Person : alice
  #30 = String             #31            // bob
  #31 = Utf8               bob
  #32 = String             #33            // new Person : bob
  #33 = Utf8               new Person : bob
  #34 = Methodref          #8.#35         // java/lang/System.identityHashCode:(Ljava/lang/Object;)I
  #35 = NameAndType        #36:#37        // identityHashCode:(Ljava/lang/Object;)I
  #36 = Utf8               identityHashCode
  #37 = Utf8               (Ljava/lang/Object;)I
  #38 = InvokeDynamic      #0:#39         // #0:makeConcatWithConstants:(I)Ljava/lang/String;
  #39 = NameAndType        #40:#41        // makeConcatWithConstants:(I)Ljava/lang/String;
  #40 = Utf8               makeConcatWithConstants
  #41 = Utf8               (I)Ljava/lang/String;
  #42 = InvokeDynamic      #1:#39         // #1:makeConcatWithConstants:(I)Ljava/lang/String;
  #43 = Fieldref           #44.#45        // src/PersonIncludeStatic.country:Ljava/lang/String;
  #44 = Class              #46            // src/PersonIncludeStatic
  #45 = NameAndType        #47:#48        // country:Ljava/lang/String;
  #46 = Utf8               src/PersonIncludeStatic
  #47 = Utf8               country
  #48 = Utf8               Ljava/lang/String;
  #49 = InvokeDynamic      #2:#50         // #2:makeConcatWithConstants:(Ljava/lang/String;)Ljava/lang/String;
  #50 = NameAndType        #40:#51        // makeConcatWithConstants:(Ljava/lang/String;)Ljava/lang/String;
  #51 = Utf8               (Ljava/lang/String;)Ljava/lang/String;
  #52 = Class              #53            // src/Main
  #53 = Utf8               src/Main
  #54 = Utf8               Code
  #55 = Utf8               LineNumberTable
  #56 = Utf8               main
  #57 = Utf8               ([Ljava/lang/String;)V
  #58 = Utf8               SourceFile
  #59 = Utf8               Main.java
  #60 = Utf8               BootstrapMethods
  #61 = MethodHandle       6:#62          // REF_invokeStatic java/lang/invoke/StringConcatFactory.makeConcatWithConstants:(Ljava/lang/invoke/MethodHandles$Lookup;Ljava/lang/String;Ljava/lang/invoke/MethodType;Ljava/lang/String;[Ljava/lang/Object;)Ljava/lang/invoke/CallSite;
  #62 = Methodref          #63.#64        // java/lang/invoke/StringConcatFactory.makeConcatWithConstants:(Ljava/lang/invoke/MethodHandles$Lookup;Ljava/lang/String;Ljava/lang/invoke/MethodType;Ljava/lang/String;[Ljava/lang/Object;)Ljava/lang/invoke/CallSite;
  #63 = Class              #65            // java/lang/invoke/StringConcatFactory
  #64 = NameAndType        #40:#66        // makeConcatWithConstants:(Ljava/lang/invoke/MethodHandles$Lookup;Ljava/lang/String;Ljava/lang/invoke/MethodType;Ljava/lang/String;[Ljava/lang/Object;)Ljava/lang/invoke/CallSite;
  #65 = Utf8               java/lang/invoke/StringConcatFactory
  #66 = Utf8               (Ljava/lang/invoke/MethodHandles$Lookup;Ljava/lang/String;Ljava/lang/invoke/MethodType;Ljava/lang/String;[Ljava/lang/Object;)Ljava/lang/invoke/CallSite;
  #67 = String             #68            // alice hash : \u0001
  #68 = Utf8               alice hash : \u0001
  #69 = String             #70            // bob   hash : \u0001
  #70 = Utf8               bob   hash : \u0001
  #71 = String             #72            // PersonWithStatic.country call \u0001
  #72 = Utf8               PersonWithStatic.country call \u0001
  #73 = Utf8               InnerClasses
  #74 = Class              #75            // java/lang/invoke/MethodHandles$Lookup
  #75 = Utf8               java/lang/invoke/MethodHandles$Lookup
  #76 = Class              #77            // java/lang/invoke/MethodHandles
  #77 = Utf8               java/lang/invoke/MethodHandles
  #78 = Utf8               Lookup
{
  public src.Main();
    descriptor: ()V
    flags: (0x0001) ACC_PUBLIC
    Code:
      stack=1, locals=1, args_size=1
         0: aload_0
         1: invokespecial #1                  // Method java/lang/Object."<init>":()V
         4: return
      LineNumberTable:
        line 2: 0

  public static void main(java.lang.String[]);
    descriptor: ([Ljava/lang/String;)V
    flags: (0x0009) ACC_PUBLIC, ACC_STATIC
    Code:
      stack=4, locals=4, args_size=1
         0: bipush        40
         2: istore_1
         3: getstatic     #7                  // Field java/lang/System.out:Ljava/io/PrintStream;
         6: ldc           #13                 // String Before new Person
         8: invokevirtual #15                 // Method java/io/PrintStream.println:(Ljava/lang/String;)V
        11: new           #21                 // class src/Person
        14: dup
        15: iload_1
        16: ldc           #23                 // String alice
        18: invokespecial #25                 // Method src/Person."<init>":(ILjava/lang/String;)V
        21: astore_2
        22: getstatic     #7                  // Field java/lang/System.out:Ljava/io/PrintStream;
        25: ldc           #28                 // String new Person : alice
        27: invokevirtual #15                 // Method java/io/PrintStream.println:(Ljava/lang/String;)V
        30: new           #21                 // class src/Person
        33: dup
        34: iload_1
        35: ldc           #30                 // String bob
        37: invokespecial #25                 // Method src/Person."<init>":(ILjava/lang/String;)V
        40: astore_3
        41: getstatic     #7                  // Field java/lang/System.out:Ljava/io/PrintStream;
        44: ldc           #32                 // String new Person : bob
        46: invokevirtual #15                 // Method java/io/PrintStream.println:(Ljava/lang/String;)V
        49: getstatic     #7                  // Field java/lang/System.out:Ljava/io/PrintStream;
        52: aload_2
        53: invokestatic  #34                 // Method java/lang/System.identityHashCode:(Ljava/lang/Object;)I
        56: invokedynamic #38,  0             // InvokeDynamic #0:makeConcatWithConstants:(I)Ljava/lang/String;
        61: invokevirtual #15                 // Method java/io/PrintStream.println:(Ljava/lang/String;)V
        64: getstatic     #7                  // Field java/lang/System.out:Ljava/io/PrintStream;
        67: aload_3
        68: invokestatic  #34                 // Method java/lang/System.identityHashCode:(Ljava/lang/Object;)I
        71: invokedynamic #42,  0             // InvokeDynamic #1:makeConcatWithConstants:(I)Ljava/lang/String;
        76: invokevirtual #15                 // Method java/io/PrintStream.println:(Ljava/lang/String;)V
        79: getstatic     #7                  // Field java/lang/System.out:Ljava/io/PrintStream;
        82: getstatic     #43                 // Field src/PersonIncludeStatic.country:Ljava/lang/String;
        85: invokedynamic #49,  0             // InvokeDynamic #2:makeConcatWithConstants:(Ljava/lang/String;)Ljava/lang/String;
        90: invokevirtual #15                 // Method java/io/PrintStream.println:(Ljava/lang/String;)V
        93: return
      LineNumberTable:
        line 4: 0
        line 5: 3
        line 6: 11
        line 7: 22
        line 8: 30
        line 9: 41
        line 10: 49
        line 11: 64
        line 12: 79
        line 13: 93
}
SourceFile: "Main.java"
BootstrapMethods:
  0: #61 REF_invokeStatic java/lang/invoke/StringConcatFactory.makeConcatWithConstants:(Ljava/lang/invoke/MethodHandles$Lookup;Ljava/lang/String;Ljava/lang/invoke/MethodType;Ljava/lang/String;[Ljava/lang/Object;)Ljava/lang/invoke/CallSite;
    Method arguments:
      #67 alice hash : \u0001
  1: #61 REF_invokeStatic java/lang/invoke/StringConcatFactory.makeConcatWithConstants:(Ljava/lang/invoke/MethodHandles$Lookup;Ljava/lang/String;Ljava/lang/invoke/MethodType;Ljava/lang/String;[Ljava/lang/Object;)Ljava/lang/invoke/CallSite;
    Method arguments:
      #69 bob   hash : \u0001
  2: #61 REF_invokeStatic java/lang/invoke/StringConcatFactory.makeConcatWithConstants:(Ljava/lang/invoke/MethodHandles$Lookup;Ljava/lang/String;Ljava/lang/invoke/MethodType;Ljava/lang/String;[Ljava/lang/Object;)Ljava/lang/invoke/CallSite;
    Method arguments:
      #71 PersonWithStatic.country call \u0001
InnerClasses:
  public static final #78= #74 of #76;    // Lookup=class java/lang/invoke/MethodHandles$Lookup of class java/lang/invoke/MethodHandles
